{"cameraMode":{"drawMode":0,"name":"Shaded","section":"Shading Mode"},"sceneLighting":true,"audioPlay":false,"sceneViewState":{"m_AlwaysRefresh":false,"showFog":true,"showSkybox":true,"showFlares":true,"showImageEffects":true,"showParticleSystems":true,"showVisualEffectGraphs":true,"m_FxEnabled":true},"in2DMode":false,"pivot":{"x":42.570655822753909,"y":-8.608015060424805,"z":-10.686259269714356},"rotation":{"x":-0.04687279462814331,"y":-0.747158408164978,"z":0.05299730971455574,"w":-0.6608931422233582},"size":44.913883209228519,"orthographic":false}